<annotation>
	<folder>train</folder>
	<filename>0110DF.jpg</filename>
	<path>C:\Users\Frank\Documents\MSc Data Science\AC53014 Machine Learning\Assignments\object_detection\data\images\train\0110DF.jpg</path>
	<source>
		<database>Unknown</database>
	</source>
	<size>
		<width>1280</width>
		<height>720</height>
		<depth>3</depth>
	</size>
	<segmented>0</segmented>
	<object>
		<name>F1 Car</name>
		<pose>Unspecified</pose>
		<truncated>0</truncated>
		<difficult>0</difficult>
		<bndbox>
			<xmin>77</xmin>
			<ymin>107</ymin>
			<xmax>1035</xmax>
			<ymax>712</ymax>
		</bndbox>
	</object>
</annotation>
